twisted/plugins/txtorcon_endpoint_parser.py
txtorcon/__init__.py
txtorcon/_metadata.py
txtorcon/_microdesc_parser.py
txtorcon/addrmap.py
txtorcon/attacher.py
txtorcon/circuit.py
txtorcon/controller.py
txtorcon/controller_py3.py
txtorcon/endpoints.py
txtorcon/interface.py
txtorcon/log.py
txtorcon/onion.py
txtorcon/router.py
txtorcon/socks.py
txtorcon/spaghetti.py
txtorcon/stream.py
txtorcon/testutil.py
txtorcon/torconfig.py
txtorcon/torcontrolprotocol.py
txtorcon/torinfo.py
txtorcon/torstate.py
txtorcon/util.py
txtorcon/web.py
txtorcon-24.8.0.data/data/share/txtorcon/INSTALL
txtorcon-24.8.0.data/data/share/txtorcon/Makefile
txtorcon-24.8.0.data/data/share/txtorcon/README.rst
txtorcon-24.8.0.data/data/share/txtorcon/TODO
txtorcon-24.8.0.data/data/share/txtorcon/apilinks_sphinxext.py
txtorcon-24.8.0.data/data/share/txtorcon/avatar.png
txtorcon-24.8.0.data/data/share/txtorcon/conf.py
txtorcon-24.8.0.data/data/share/txtorcon/examples.rst
txtorcon-24.8.0.data/data/share/txtorcon/guide.rst
txtorcon-24.8.0.data/data/share/txtorcon/hacking.rst
txtorcon-24.8.0.data/data/share/txtorcon/haiku.css
txtorcon-24.8.0.data/data/share/txtorcon/index.rst
txtorcon-24.8.0.data/data/share/txtorcon/installing.rst
txtorcon-24.8.0.data/data/share/txtorcon/interop_asyncio.rst
txtorcon-24.8.0.data/data/share/txtorcon/introduction.rst
txtorcon-24.8.0.data/data/share/txtorcon/logo.png
txtorcon-24.8.0.data/data/share/txtorcon/logo.svg
txtorcon-24.8.0.data/data/share/txtorcon/meejah.asc
txtorcon-24.8.0.data/data/share/txtorcon/release-checklist.rst
txtorcon-24.8.0.data/data/share/txtorcon/releases.rst
txtorcon-24.8.0.data/data/share/txtorcon/txtorcon-config.rst
txtorcon-24.8.0.data/data/share/txtorcon/txtorcon-controller.rst
txtorcon-24.8.0.data/data/share/txtorcon/txtorcon-endpoints.rst
txtorcon-24.8.0.data/data/share/txtorcon/txtorcon-interface.rst
txtorcon-24.8.0.data/data/share/txtorcon/txtorcon-onion.rst
txtorcon-24.8.0.data/data/share/txtorcon/txtorcon-protocol.rst
txtorcon-24.8.0.dist-info/LICENSE
txtorcon-24.8.0.dist-info/METADATA
txtorcon-24.8.0.dist-info/WHEEL
txtorcon-24.8.0.dist-info/top_level.txt
txtorcon-24.8.0.dist-info/RECORD
