Metadata-Version: 2.1
Name: txtorcon
Version: 24.8.0
Summary:      Twisted-based Tor controller client, with state-tracking and     configuration abstractions.     https://txtorcon.readthedocs.org     https://github.com/meejah/txtorcon 
Home-page: https://github.com/meejah/txtorcon
Author: meejah
Author-email: meejah@meejah.ca
License: MIT
Keywords: python,twisted,tor,tor controller
Classifier: Framework :: Twisted
Classifier: Development Status :: 4 - Beta
Classifier: Intended Audience :: Developers
Classifier: License :: OSI Approved :: MIT License
Classifier: Natural Language :: English
Classifier: Operating System :: POSIX :: Linux
Classifier: Operating System :: Unix
Classifier: Programming Language :: Python
Classifier: Programming Language :: Python :: 3
Classifier: Topic :: Software Development :: Libraries :: Python Modules
Classifier: Topic :: Internet :: Proxy Servers
Classifier: Topic :: Internet
Classifier: Topic :: Security
Requires-Python: >=3.8
Provides-Extra: dev
License-File: LICENSE
